[
  {
    "home": "United States",
    "away": "Belgium",
    "fecha": "2026-07-07T00:00:00Z",
    "estado": "finished",
    "odds": {},
    "prediction": {
      "recommendation": "⚠️ Sin datos"
    }
  },
  {
    "home": "Argentina",
    "away": "Egypt",
    "fecha": "2026-07-07T16:00:00Z",
    "estado": "live",
    "odds": {
      "bookmakers": [
        {
          "title": "Unibet (NL)",
          "markets": [
            {
              "outcomes": [
                {
                  "name": "Argentina",
                  "price": 1.35
                },
                {
                  "name": "Egypt",
                  "price": 10.0
                },
                {
                  "name": "Draw",
                  "price": 4.25
                }
              ]
            }
          ]
        },
        {
          "title": "Unibet (SE)",
          "markets": [
            {
              "outcomes": [
                {
                  "name": "Argentina",
                  "price": 1.35
                },
                {
                  "name": "Egypt",
                  "price": 10.0
                },
                {
                  "name": "Draw",
                  "price": 4.25
                }
              ]
            }
          ]
        },
        {
          "title": "Tipico",
          "markets": [
            {
              "outcomes": [
                {
                  "name": "Argentina",
                  "price": 1.35
                },
                {
                  "name": "Egypt",
                  "price": 10.0
                },
                {
                  "name": "Draw",
                  "price": 4.5
                }
              ]
            }
          ]
        },
        {
          "title": "LeoVegas (SE)",
          "markets": [
            {
              "outcomes": [
                {
                  "name": "Argentina",
                  "price": 1.28
                },
                {
                  "name": "Egypt",
                  "price": 9.5
                },
                {
                  "name": "Draw",
                  "price": 4.0
                }
              ]
            }
          ]
        },
        {
          "title": "PMU (FR)",
          "markets": [
            {
              "outcomes": [
                {
                  "name": "Argentina",
                  "price": 1.35
                },
                {
                  "name": "Egypt",
                  "price": 10.0
                },
                {
                  "name": "Draw",
                  "price": 4.25
                }
              ]
            }
          ]
        },
        {
          "title": "Marathon Bet",
          "markets": [
            {
              "outcomes": [
                {
                  "name": "Argentina",
                  "price": 1.34
                },
                {
                  "name": "Egypt",
                  "price": 11.25
                },
                {
                  "name": "Draw",
                  "price": 4.7
                }
              ]
            }
          ]
        },
        {
          "title": "GTbets",
          "markets": [
            {
              "outcomes": [
                {
                  "name": "Argentina",
                  "price": 1.34
                },
                {
                  "name": "Egypt",
                  "price": 10.8
                },
                {
                  "name": "Draw",
                  "price": 5.0
                }
              ]
            }
          ]
        },
        {
          "title": "Unibet (FR)",
          "markets": [
            {
              "outcomes": [
                {
                  "name": "Argentina",
                  "price": 1.3
                },
                {
                  "name": "Egypt",
                  "price": 12.0
                },
                {
                  "name": "Draw",
                  "price": 5.0
                }
              ]
            }
          ]
        },
        {
          "title": "Betclic (FR)",
          "markets": [
            {
              "outcomes": [
                {
                  "name": "Argentina",
                  "price": 1.35
                },
                {
                  "name": "Egypt",
                  "price": 10.0
                },
                {
                  "name": "Draw",
                  "price": 4.2
                }
              ]
            }
          ]
        },
        {
          "title": "MyBookie.ag",
          "markets": [
            {
              "outcomes": [
                {
                  "name": "Argentina",
                  "price": 1.35
                },
                {
                  "name": "Egypt",
                  "price": 10.25
                },
                {
                  "name": "Draw",
                  "price": 4.2
                }
              ]
            }
          ]
        },
        {
          "title": "1xBet",
          "markets": [
            {
              "outcomes": [
                {
                  "name": "Argentina",
                  "price": 1.37
                },
                {
                  "name": "Egypt",
                  "price": 10.6
                },
                {
                  "name": "Draw",
                  "price": 4.84
                }
              ]
            }
          ]
        },
        {
          "title": "Winamax (DE)",
          "markets": [
            {
              "outcomes": [
                {
                  "name": "Argentina",
                  "price": 1.38
                },
                {
                  "name": "Egypt",
                  "price": 8.5
                },
                {
                  "name": "Draw",
                  "price": 4.2
                }
              ]
            }
          ]
        },
        {
          "title": "Winamax (FR)",
          "markets": [
            {
              "outcomes": [
                {
                  "name": "Argentina",
                  "price": 1.34
                },
                {
                  "name": "Egypt",
                  "price": 8.5
                },
                {
                  "name": "Draw",
                  "price": 4.1
                }
              ]
            }
          ]
        },
        {
          "title": "Pinnacle",
          "markets": [
            {
              "outcomes": [
                {
                  "name": "Argentina",
                  "price": 1.36
                },
                {
                  "name": "Egypt",
                  "price": 11.75
                },
                {
                  "name": "Draw",
                  "price": 4.8
                }
              ]
            }
          ]
        },
        {
          "title": "Matchbook",
          "markets": [
            {
              "outcomes": [
                {
                  "name": "Argentina",
                  "price": 1.4
                },
                {
                  "name": "Egypt",
                  "price": 12.5
                },
                {
                  "name": "Draw",
                  "price": 4.8
                }
              ]
            }
          ]
        },
        {
          "title": "888sport",
          "markets": [
            {
              "outcomes": [
                {
                  "name": "Argentina",
                  "price": 1.3
                },
                {
                  "name": "Egypt",
                  "price": 9.5
                },
                {
                  "name": "Draw",
                  "price": 4.33
                }
              ]
            }
          ]
        },
        {
          "title": "William Hill",
          "markets": [
            {
              "outcomes": [
                {
                  "name": "Argentina",
                  "price": 1.33
                },
                {
                  "name": "Egypt",
                  "price": 10.0
                },
                {
                  "name": "Draw",
                  "price": 4.5
                }
              ]
            }
          ]
        },
        {
          "title": "Betfair",
          "markets": [
            {
              "outcomes": [
                {
                  "name": "Argentina",
                  "price": 1.4
                },
                {
                  "name": "Egypt",
                  "price": 11.5
                },
                {
                  "name": "Draw",
                  "price": 4.9
                }
              ]
            }
          ]
        },
        {
          "title": "Coolbet",
          "markets": [
            {
              "outcomes": [
                {
                  "name": "Argentina",
                  "price": 1.4
                },
                {
                  "name": "Egypt",
                  "price": 10.25
                },
                {
                  "name": "Draw",
                  "price": 4.55
                }
              ]
            }
          ]
        },
        {
          "title": "BetOnline.ag",
          "markets": [
            {
              "outcomes": [
                {
                  "name": "Argentina",
                  "price": 1.36
                },
                {
                  "name": "Egypt",
                  "price": 11.7
                },
                {
                  "name": "Draw",
                  "price": 4.8
                }
              ]
            }
          ]
        },
        {
          "title": "Betsson",
          "markets": [
            {
              "outcomes": [
                {
                  "name": "Argentina",
                  "price": 1.33
                },
                {
                  "name": "Egypt",
                  "price": 12.0
                },
                {
                  "name": "Draw",
                  "price": 4.3
                }
              ]
            }
          ]
        },
        {
          "title": "Nordic Bet",
          "markets": [
            {
              "outcomes": [
                {
                  "name": "Argentina",
                  "price": 1.33
                },
                {
                  "name": "Egypt",
                  "price": 12.0
                },
                {
                  "name": "Draw",
                  "price": 4.3
                }
              ]
            }
          ]
        },
        {
          "title": "Everygame",
          "markets": [
            {
              "outcomes": [
                {
                  "name": "Argentina",
                  "price": 1.33
                },
                {
                  "name": "Egypt",
                  "price": 11.0
                },
                {
                  "name": "Draw",
                  "price": 4.75
                }
              ]
            }
          ]
        },
        {
          "title": "Codere (IT)",
          "markets": [
            {
              "outcomes": [
                {
                  "name": "Argentina",
                  "price": 1.33
                },
                {
                  "name": "Egypt",
                  "price": 11.0
                },
                {
                  "name": "Draw",
                  "price": 4.9
                }
              ]
            }
          ]
        },
        {
          "title": "BetAnything",
          "markets": [
            {
              "outcomes": [
                {
                  "name": "Argentina",
                  "price": 1.33
                },
                {
                  "name": "Egypt",
                  "price": 11.0
                },
                {
                  "name": "Draw",
                  "price": 4.75
                }
              ]
            }
          ]
        }
      ],
      "home_win": 1.33,
      "away_win": 11.0,
      "draw": 4.75,
      "over_under": [
        {
          "name": "Over",
          "line": 2.5,
          "price": 2.2
        },
        {
          "name": "Under",
          "line": 2.5,
          "price": 1.62
        }
      ],
      "handicap": [
        {
          "name": "Argentina",
          "line": -1.5,
          "price": 2.05
        },
        {
          "name": "Egypt",
          "line": 1.5,
          "price": 1.79
        }
      ]
    },
    "prediction": {
      "prob_home": 0.71,
      "prob_draw": 0.2,
      "prob_away": 0.09,
      "ev_home": 0.94,
      "ev_draw": 0.95,
      "ev_away": 0.99,
      "recommendation": "PASS",
      "best_ev": 0.99
    }
  },
  {
    "home": "Switzerland",
    "away": "Colombia",
    "fecha": "2026-07-07T20:00:00Z",
    "estado": "timed",
    "odds": {
      "bookmakers": [
        {
          "title": "LeoVegas (SE)",
          "markets": [
            {
              "outcomes": [
                {
                  "name": "Colombia",
                  "price": 2.23
                },
                {
                  "name": "Switzerland",
                  "price": 3.65
                },
                {
                  "name": "Draw",
                  "price": 3.05
                }
              ]
            }
          ]
        },
        {
          "title": "Tipico",
          "markets": [
            {
              "outcomes": [
                {
                  "name": "Colombia",
                  "price": 2.25
                },
                {
                  "name": "Switzerland",
                  "price": 3.5
                },
                {
                  "name": "Draw",
                  "price": 3.1
                }
              ]
            }
          ]
        },
        {
          "title": "PMU (FR)",
          "markets": [
            {
              "outcomes": [
                {
                  "name": "Colombia",
                  "price": 2.28
                },
                {
                  "name": "Switzerland",
                  "price": 3.6
                },
                {
                  "name": "Draw",
                  "price": 3.15
                }
              ]
            }
          ]
        },
        {
          "title": "Unibet (SE)",
          "markets": [
            {
              "outcomes": [
                {
                  "name": "Colombia",
                  "price": 2.28
                },
                {
                  "name": "Switzerland",
                  "price": 3.75
                },
                {
                  "name": "Draw",
                  "price": 3.15
                }
              ]
            }
          ]
        },
        {
          "title": "Unibet (NL)",
          "markets": [
            {
              "outcomes": [
                {
                  "name": "Colombia",
                  "price": 2.28
                },
                {
                  "name": "Switzerland",
                  "price": 3.75
                },
                {
                  "name": "Draw",
                  "price": 3.15
                }
              ]
            }
          ]
        },
        {
          "title": "Marathon Bet",
          "markets": [
            {
              "outcomes": [
                {
                  "name": "Colombia",
                  "price": 2.25
                },
                {
                  "name": "Switzerland",
                  "price": 3.64
                },
                {
                  "name": "Draw",
                  "price": 3.05
                }
              ]
            }
          ]
        },
        {
          "title": "Betclic (FR)",
          "markets": [
            {
              "outcomes": [
                {
                  "name": "Colombia",
                  "price": 2.22
                },
                {
                  "name": "Switzerland",
                  "price": 3.75
                },
                {
                  "name": "Draw",
                  "price": 3.1
                }
              ]
            }
          ]
        },
        {
          "title": "Codere (IT)",
          "markets": [
            {
              "outcomes": [
                {
                  "name": "Colombia",
                  "price": 2.26
                },
                {
                  "name": "Switzerland",
                  "price": 3.5
                },
                {
                  "name": "Draw",
                  "price": 3.1
                }
              ]
            }
          ]
        },
        {
          "title": "Unibet (FR)",
          "markets": [
            {
              "outcomes": [
                {
                  "name": "Colombia",
                  "price": 2.15
                },
                {
                  "name": "Switzerland",
                  "price": 3.85
                },
                {
                  "name": "Draw",
                  "price": 3.2
                }
              ]
            }
          ]
        },
        {
          "title": "MyBookie.ag",
          "markets": [
            {
              "outcomes": [
                {
                  "name": "Colombia",
                  "price": 2.15
                },
                {
                  "name": "Switzerland",
                  "price": 3.6
                },
                {
                  "name": "Draw",
                  "price": 3.16
                }
              ]
            }
          ]
        },
        {
          "title": "GTbets",
          "markets": [
            {
              "outcomes": [
                {
                  "name": "Colombia",
                  "price": 2.31
                },
                {
                  "name": "Switzerland",
                  "price": 3.58
                },
                {
                  "name": "Draw",
                  "price": 3.13
                }
              ]
            }
          ]
        },
        {
          "title": "Winamax (DE)",
          "markets": [
            {
              "outcomes": [
                {
                  "name": "Colombia",
                  "price": 2.25
                },
                {
                  "name": "Switzerland",
                  "price": 3.55
                },
                {
                  "name": "Draw",
                  "price": 3.15
                }
              ]
            }
          ]
        },
        {
          "title": "Winamax (FR)",
          "markets": [
            {
              "outcomes": [
                {
                  "name": "Colombia",
                  "price": 2.2
                },
                {
                  "name": "Switzerland",
                  "price": 3.5
                },
                {
                  "name": "Draw",
                  "price": 3.1
                }
              ]
            }
          ]
        },
        {
          "title": "1xBet",
          "markets": [
            {
              "outcomes": [
                {
                  "name": "Colombia",
                  "price": 2.32
                },
                {
                  "name": "Switzerland",
                  "price": 3.75
                },
                {
                  "name": "Draw",
                  "price": 3.15
                }
              ]
            }
          ]
        },
        {
          "title": "Matchbook",
          "markets": [
            {
              "outcomes": [
                {
                  "name": "Colombia",
                  "price": 2.36
                },
                {
                  "name": "Switzerland",
                  "price": 3.8
                },
                {
                  "name": "Draw",
                  "price": 3.15
                }
              ]
            }
          ]
        },
        {
          "title": "Pinnacle",
          "markets": [
            {
              "outcomes": [
                {
                  "name": "Colombia",
                  "price": 2.3
                },
                {
                  "name": "Switzerland",
                  "price": 3.76
                },
                {
                  "name": "Draw",
                  "price": 3.1
                }
              ]
            }
          ]
        },
        {
          "title": "Coolbet",
          "markets": [
            {
              "outcomes": [
                {
                  "name": "Colombia",
                  "price": 2.32
                },
                {
                  "name": "Switzerland",
                  "price": 3.7
                },
                {
                  "name": "Draw",
                  "price": 3.1
                }
              ]
            }
          ]
        },
        {
          "title": "BetOnline.ag",
          "markets": [
            {
              "outcomes": [
                {
                  "name": "Colombia",
                  "price": 2.29
                },
                {
                  "name": "Switzerland",
                  "price": 3.73
                },
                {
                  "name": "Draw",
                  "price": 3.08
                }
              ]
            }
          ]
        },
        {
          "title": "Nordic Bet",
          "markets": [
            {
              "outcomes": [
                {
                  "name": "Colombia",
                  "price": 2.3
                },
                {
                  "name": "Switzerland",
                  "price": 3.65
                },
                {
                  "name": "Draw",
                  "price": 3.1
                }
              ]
            }
          ]
        },
        {
          "title": "Betsson",
          "markets": [
            {
              "outcomes": [
                {
                  "name": "Colombia",
                  "price": 2.3
                },
                {
                  "name": "Switzerland",
                  "price": 3.65
                },
                {
                  "name": "Draw",
                  "price": 3.1
                }
              ]
            }
          ]
        },
        {
          "title": "Betfair",
          "markets": [
            {
              "outcomes": [
                {
                  "name": "Colombia",
                  "price": 2.36
                },
                {
                  "name": "Switzerland",
                  "price": 3.75
                },
                {
                  "name": "Draw",
                  "price": 3.15
                }
              ]
            }
          ]
        },
        {
          "title": "888sport",
          "markets": [
            {
              "outcomes": [
                {
                  "name": "Colombia",
                  "price": 2.2
                },
                {
                  "name": "Switzerland",
                  "price": 3.4
                },
                {
                  "name": "Draw",
                  "price": 2.9
                }
              ]
            }
          ]
        },
        {
          "title": "William Hill",
          "markets": [
            {
              "outcomes": [
                {
                  "name": "Colombia",
                  "price": 2.2
                },
                {
                  "name": "Switzerland",
                  "price": 3.5
                },
                {
                  "name": "Draw",
                  "price": 2.9
                }
              ]
            }
          ]
        },
        {
          "title": "Everygame",
          "markets": [
            {
              "outcomes": [
                {
                  "name": "Colombia",
                  "price": 2.25
                },
                {
                  "name": "Switzerland",
                  "price": 3.6
                },
                {
                  "name": "Draw",
                  "price": 3.05
                }
              ]
            }
          ]
        },
        {
          "title": "BetAnything",
          "markets": [
            {
              "outcomes": [
                {
                  "name": "Colombia",
                  "price": 2.3
                },
                {
                  "name": "Switzerland",
                  "price": 3.55
                },
                {
                  "name": "Draw",
                  "price": 3.05
                }
              ]
            }
          ]
        }
      ],
      "away_win": 2.3,
      "home_win": 3.55,
      "draw": 3.05,
      "over_under": [
        {
          "name": "Over",
          "line": 2.5,
          "price": 2.23
        },
        {
          "name": "Under",
          "line": 2.5,
          "price": 1.56
        }
      ],
      "handicap": [
        {
          "name": "Colombia",
          "line": -0.5,
          "price": 2.14
        },
        {
          "name": "Switzerland",
          "line": 0.5,
          "price": 1.71
        }
      ]
    },
    "prediction": {
      "prob_home": 0.27,
      "prob_draw": 0.31,
      "prob_away": 0.42,
      "ev_home": 0.96,
      "ev_draw": 0.95,
      "ev_away": 0.97,
      "recommendation": "PASS",
      "best_ev": 0.97
    }
  }
]